_examples/__init__.py
examples/__init__.py
mixins/__init__.py
mixins/attrequals.py
mixins/propertycache.py
mixins/repr.py
tests/__init__.py
tests/test_repr.py
mixins-0.1.4.dist-info/LICENSE.md
mixins-0.1.4.dist-info/METADATA
mixins-0.1.4.dist-info/WHEEL
mixins-0.1.4.dist-info/entry_points.txt
mixins-0.1.4.dist-info/top_level.txt
mixins-0.1.4.dist-info/RECORD
